flask_hsrpc/__init__.py
flask_hsrpc/__version__.py
flask_hsrpc/api_requests.py
flask_hsrpc/consul.py
flask_hsrpc/default_decorator.py
flask_hsrpc/log.py
flask_hsrpc/response.py
flask_hsrpc/swagger.py
flask_hsrpc/request_parser/__init__.py
flask_hsrpc/request_parser/fields.py
flask_hsrpc/request_parser/validators.py
flask_hsrpc-0.1.15.dist-info/DESCRIPTION.rst
flask_hsrpc-0.1.15.dist-info/METADATA
flask_hsrpc-0.1.15.dist-info/RECORD
flask_hsrpc-0.1.15.dist-info/WHEEL
flask_hsrpc-0.1.15.dist-info/metadata.json
flask_hsrpc-0.1.15.dist-info/top_level.txt
